taos/__init__.py
taos/_version.py
taos/bind.py
taos/bind2.py
taos/bind_base.py
taos/cinterface.py
taos/connection.py
taos/constants.py
taos/cursor.py
taos/error.py
taos/field.py
taos/field_v3.py
taos/log.py
taos/precision.py
taos/result.py
taos/schemaless.py
taos/sqlalchemy.py
taos/statement.py
taos/statement2.py
taos/subscription.py
taos/tmq.py
taos/utils.py
taosrest/__init__.py
taosrest/connection.py
taosrest/cursor.py
taosrest/errors.py
taosrest/restclient.py
taosrest/sqlalchemy.py
taospy-2.8.8.dist-info/entry_points.txt
taospy-2.8.8.dist-info/LICENSE
taospy-2.8.8.dist-info/WHEEL
taospy-2.8.8.dist-info/METADATA
taospy-2.8.8.dist-info/RECORD
