Metadata-Version: 2.1
Name: taospy
Version: 2.8.8
Summary: The official TDengine Python connector
License: MIT
Author: Taosdata Inc.
Author-email: support@taosdata.com
Requires-Python: >=3.7,<4.0
Classifier: License :: OSI Approved :: MIT License
Classifier: Programming Language :: Python :: 3
Classifier: Programming Language :: Python :: 3.7
Classifier: Programming Language :: Python :: 3.8
Classifier: Programming Language :: Python :: 3.9
Classifier: Programming Language :: Python :: 3.10
Provides-Extra: ws
Requires-Dist: iso8601 (==1.0.2)
Requires-Dist: pytz
Requires-Dist: requests (>=2.27.1)
Requires-Dist: taos-ws-py (>=0.3.0); (python_version >= "3.7" and python_version < "4.0") and (extra == "ws")
Requires-Dist: typing-extensions (>=4.2.0,<4.15.0)
